stsutility/__init__.py
stsutility-0.0.6.dist-info/LICENSE.txt
stsutility-0.0.6.dist-info/METADATA
stsutility-0.0.6.dist-info/WHEEL
stsutility-0.0.6.dist-info/top_level.txt
stsutility-0.0.6.dist-info/RECORD
