Metadata-Version: 2.1
Name: stsutility
Version: 0.0.6
Summary: 636 Utility Package
Home-page: https://github.com/0187773933/stsutility
Author: 636
Author-email: win.stitch.23@gmail.com
License: UNKNOWN
Platform: UNKNOWN
Classifier: Programming Language :: Python :: 3
Classifier: License :: OSI Approved :: MIT License
Classifier: Operating System :: OS Independent
Requires-Python: >=3.6
Requires-Dist: json
Requires-Dist: pathlib
Requires-Dist: time
Requires-Dist: Pint
Requires-Dist: math
Requires-Dist: decimal
Requires-Dist: operator
Requires-Dist: pandas
Requires-Dist: numpy
Requires-Dist: pprint
